README.rst
setup.py
tests/__init__.py
tests/base.py
tests/test_external_commands.py
tests/test_fs_util.py
tests/test_logging.py
tests/test_text_manipulations.py
yugabyte_pycommon/__init__.py
yugabyte_pycommon/collection_util.py
yugabyte_pycommon/external_calls.py
yugabyte_pycommon/fs_util.py
yugabyte_pycommon/logging_util.py
yugabyte_pycommon/text_manipulation.py
yugabyte_pycommon/update_version.py
yugabyte_pycommon/version.py
yugabyte_pycommon.egg-info/PKG-INFO
yugabyte_pycommon.egg-info/SOURCES.txt
yugabyte_pycommon.egg-info/dependency_links.txt
yugabyte_pycommon.egg-info/entry_points.txt
yugabyte_pycommon.egg-info/requires.txt
yugabyte_pycommon.egg-info/top_level.txt