Metadata-Version: 2.1
Name: yugabyte-pycommon
Version: 1.9.15
Summary: Common utilities used in YugaByte Database's build infrastructure but could also be useful for anyone. E.g. convenient utilities for running external programs, logging, etc. Please give YugaByte DB a star at https://github.com/yugabyte/yugabyte-db -- much appreciated!
Home-page: https://github.com/yugabyte/yugabyte_pycommon
Author: YugaByte, Inc.
Author-email: mbautin@users.noreply.github.com
License: Apache 2.0
Keywords: tool tools utility utilities yugabyte run command external process group_by
Platform: UNKNOWN
Classifier: Development Status :: 4 - Beta
Classifier: Intended Audience :: Developers
Classifier: Natural Language :: English
Classifier: Operating System :: Unix
Classifier: Programming Language :: Python :: 2.7
Classifier: Programming Language :: Python :: 3.4
Classifier: Programming Language :: Python :: Implementation :: PyPy
Classifier: Operating System :: OS Independent
Provides-Extra: docs
Provides-Extra: tests
Provides-Extra: release
